flyai/___init___.py
flyai/example.py
openaix-0.0.1.dist-info/METADATA
openaix-0.0.1.dist-info/WHEEL
openaix-0.0.1.dist-info/licenses/LICENSE
openaix-0.0.1.dist-info/RECORD
